multiplex2brightfield/__init__.py
multiplex2brightfield/configuration_presets.py
multiplex2brightfield/converter.py
multiplex2brightfield/enhancement.py
multiplex2brightfield/llm_utils.py
multiplex2brightfield/tiff_utils.py
multiplex2brightfield/utils.py
multiplex2brightfield-0.2.7.dist-info/LICENSE
multiplex2brightfield-0.2.7.dist-info/METADATA
multiplex2brightfield-0.2.7.dist-info/WHEEL
multiplex2brightfield-0.2.7.dist-info/top_level.txt
multiplex2brightfield-0.2.7.dist-info/RECORD
