Metadata-Version: 2.1
Name: multiplex2brightfield
Version: 0.2.7
Summary: A package to convert a multiplex image in OME-TIFF file format to a virtual brightfield image such as H&E or IHC.
Home-page: https://github.com/TristanWhitmarsh/multiplex2brightfield
Author: Tristan Whitmarsh
Author-email: tw401@cam.ac.uk
License: UNKNOWN
Platform: UNKNOWN
Classifier: Development Status :: 3 - Alpha
Classifier: Intended Audience :: Science/Research
Classifier: License :: OSI Approved :: BSD License
Classifier: Programming Language :: Python :: 3
Classifier: Topic :: Scientific/Engineering :: Bio-Informatics
Requires-Python: >=3.9
License-File: LICENSE
Requires-Dist: tensorflow (==2.14.1)
Requires-Dist: numpy (==1.26.4)
Requires-Dist: tifffile (>=2024.8.30)
Requires-Dist: scikit-image (>=0.24.0)
Requires-Dist: numpy2ometiff (>=0.1.4)
Requires-Dist: csbdeep (>=0.8.1)
Requires-Dist: SimpleITK (>=2.4.0)
Requires-Dist: lxml (>=5.3.0)
Requires-Dist: requests (>=2.32.3)
Requires-Dist: tqdm (>=4.66.5)
Requires-Dist: psutil (>=6.0.0)
Requires-Dist: protobuf (==3.20.3)
Provides-Extra: enhance
Requires-Dist: keras (>=2.10.0) ; extra == 'enhance'
Provides-Extra: llm
Requires-Dist: openai (>=1.52.0) ; extra == 'llm'
Requires-Dist: google-generativeai (>=0.8.3) ; extra == 'llm'
Requires-Dist: anthropic (>=0.37.1) ; extra == 'llm'
